Jersey2XYonghuZhinan/README.md
Jersey2XYonghuZhinan/__init__.py
Jersey2XYonghuZhinan/__main__.py
Jersey2XYonghuZhinan/file.epub
Jersey2XYonghuZhinan/index.html
Jersey2XYonghuZhinan/css/__init__.py
Jersey2XYonghuZhinan/css/annotations.css
Jersey2XYonghuZhinan/css/main.css
Jersey2XYonghuZhinan/css/normalize.css
Jersey2XYonghuZhinan/css/popup.css
Jersey2XYonghuZhinan/font/__init__.py
Jersey2XYonghuZhinan/font/fontello.eot
Jersey2XYonghuZhinan/font/fontello.svg
Jersey2XYonghuZhinan/font/fontello.ttf
Jersey2XYonghuZhinan/font/fontello.woff
Jersey2XYonghuZhinan/img/__init__.py
Jersey2XYonghuZhinan/img/annotator-glyph-sprite.png
Jersey2XYonghuZhinan/img/annotator-icon-sprite.png
Jersey2XYonghuZhinan/img/apple-touch-icon.png
Jersey2XYonghuZhinan/img/cancelfullscreen.png
Jersey2XYonghuZhinan/img/close.png
Jersey2XYonghuZhinan/img/fullscreen.png
Jersey2XYonghuZhinan/img/loader.gif
Jersey2XYonghuZhinan/img/menu-icon.png
Jersey2XYonghuZhinan/img/save.png
Jersey2XYonghuZhinan/img/saved.png
Jersey2XYonghuZhinan/img/settings-s.png
Jersey2XYonghuZhinan/img/settings.png
Jersey2XYonghuZhinan/img/star.png
Jersey2XYonghuZhinan/js/__init__.py
Jersey2XYonghuZhinan/js/epub.js
Jersey2XYonghuZhinan/js/epub.min.js
Jersey2XYonghuZhinan/js/epub.min.map
Jersey2XYonghuZhinan/js/hooks.min.js
Jersey2XYonghuZhinan/js/hooks.min.map
Jersey2XYonghuZhinan/js/reader.js
Jersey2XYonghuZhinan/js/reader.js.map
Jersey2XYonghuZhinan/js/reader.min.js
Jersey2XYonghuZhinan/js/reader.min.map
Jersey2XYonghuZhinan/js/hooks/__init__.py
Jersey2XYonghuZhinan/js/hooks/extensions/__init__.py
Jersey2XYonghuZhinan/js/hooks/extensions/highlight.js
Jersey2XYonghuZhinan/js/libs/__init__.py
Jersey2XYonghuZhinan/js/libs/jquery.min.js
Jersey2XYonghuZhinan/js/libs/localforage.min.js
Jersey2XYonghuZhinan/js/libs/screenfull.js
Jersey2XYonghuZhinan/js/libs/screenfull.min.js
Jersey2XYonghuZhinan/js/libs/zip.min.js
Jersey2XYonghuZhinan/js/plugins/__init__.py
Jersey2XYonghuZhinan/js/plugins/hypothesis.js
jersey_2_x_yonghu_zhinan-2024.3.2.0.dist-info/METADATA
jersey_2_x_yonghu_zhinan-2024.3.2.0.dist-info/WHEEL
jersey_2_x_yonghu_zhinan-2024.3.2.0.dist-info/entry_points.txt
jersey_2_x_yonghu_zhinan-2024.3.2.0.dist-info/top_level.txt
jersey_2_x_yonghu_zhinan-2024.3.2.0.dist-info/RECORD
